gai/__init__.py
gai/cli.py
gai/ollama_client.py
gai/openai_client.py
gai/provider.py
gai/utils.py
gai_commit-0.1.2.dist-info/licenses/LICENSE
gai_commit-0.1.2.dist-info/METADATA
gai_commit-0.1.2.dist-info/WHEEL
gai_commit-0.1.2.dist-info/entry_points.txt
gai_commit-0.1.2.dist-info/top_level.txt
gai_commit-0.1.2.dist-info/RECORD
